powpy/__init__.py
powpy-0.1.1.dist-info/METADATA
powpy-0.1.1.dist-info/RECORD
powpy-0.1.1.dist-info/WHEEL
powpy-0.1.1.dist-info/top_level.txt
