Metadata-Version: 2.1
Name: powpy
Version: 0.1.1
Summary: A simple proof of work using SHA-256 hashes
Home-page: https://github.com/Pineapple6/powpy
Author: Pinneaple6
Author-email: 
License: UNKNOWN
Platform: UNKNOWN
Classifier: Programming Language :: Python :: 3
Classifier: License :: OSI Approved :: MIT License
Classifier: Operating System :: OS Independent
